breeze_email_reports/EmailGiverReport.py
breeze_email_reports/EmailProfileReport.py
breeze_email_reports/_common.py
breeze_email_reports/table_format.py
breeze_email_reports-1.2.0.1.dist-info/LICENSE
breeze_email_reports-1.2.0.1.dist-info/METADATA
breeze_email_reports-1.2.0.1.dist-info/WHEEL
breeze_email_reports-1.2.0.1.dist-info/entry_points.txt
breeze_email_reports-1.2.0.1.dist-info/top_level.txt
breeze_email_reports-1.2.0.1.dist-info/RECORD
