Metadata-Version: 2.1
Name: breeze_email_reports
Version: 1.2.0.1
Summary: Utilities to email Breeze CHMS reports
Author-email: "David A. Willcox" <daw30410@yahoo.com>
License:                                  Apache License
Project-URL: Homepage, https://github.com/dawillcox/breeze_email_reports
Project-URL: Bug Tracker, https://github.com/dawillcox/breeze_email_reports/issues
Project-URL: README, https://github.com/dawillcox/breeze_email_reports/blob/master/README.rst
Project-URL: DOCUMENTATION, https://github.com/dawillcox/breeze_email_reports/blob/master/DOCUMENTATION.rst
Project-URL: CHANGELOG, https://github.com/dawillcox/breeze_email_reports/blob/master/CHANGELOG.md
Project-URL: REPOSITORY, https://github.com/dawillcox/breeze_email_reports.git
Classifier: Programming Language :: Python :: 3
Classifier: License :: OSI Approved :: Apache Software License
Classifier: Operating System :: OS Independent
Classifier: Intended Audience :: Developers
Classifier: Natural Language :: English
Requires-Python: >=3.7
License-File: LICENSE
Requires-Dist: breeze_chms_api>=1.4.4
Requires-Dist: configured_mail_sender>=1.1.0
